no_exception/__init__.py
no_exception/no_exception.py
no_exception-1.0.0.dist-info/LICENSE
no_exception-1.0.0.dist-info/METADATA
no_exception-1.0.0.dist-info/WHEEL
no_exception-1.0.0.dist-info/top_level.txt
no_exception-1.0.0.dist-info/RECORD
