Metadata-Version: 2.1
Name: no-exception
Version: 1.0.0
Summary: A package for with block that ignores exceptions
Author-email: Omer Dagry <omerdagry@gmail.com>
License: MIT License
Project-URL: Homepage, https://github.com/Omer-Dagry/WithNoException
Project-URL: Issues, https://github.com/Omer-Dagry/WithNoException/issues
Keywords: try,except,exception,handling,with
Classifier: Operating System :: OS Independent
Classifier: License :: OSI Approved :: MIT License
Classifier: Programming Language :: Python :: 3
Requires-Python: >=3
License-File: LICENSE
